django_bouncy/__init__.py
django_bouncy/admin.py
django_bouncy/models.py
django_bouncy/signals.py
django_bouncy/urls.py
django_bouncy/utils.py
django_bouncy/views.py
django_bouncy/migrations/0001_initial.py
django_bouncy/migrations/0002_auto_20150927_1413.py
django_bouncy/migrations/0003_auto_20151106_1626.py
django_bouncy/migrations/0004_increase_processing_time.py
django_bouncy/migrations/__init__.py
django_bouncy/tests/__init__.py
django_bouncy/tests/helpers.py
django_bouncy/tests/utils.py
django_bouncy/tests/views.py
django_bouncy/tests/examples/SimpleNotificationService-e372f8ca30337fdb084e8ac449342c77.pem
django_bouncy/tests/examples/example_bounce.json
django_bouncy/tests/examples/example_bounce_nocode.json
django_bouncy/tests/examples/example_bounce_notification.json
django_bouncy/tests/examples/example_complaint.json
django_bouncy/tests/examples/example_complaint_nofeedback.json
django_bouncy/tests/examples/example_complaint_notification.json
django_bouncy/tests/examples/example_confirmsubscription.xml
django_bouncy/tests/examples/example_delivery.json
django_bouncy/tests/examples/example_delivery_notification.json
django_bouncy/tests/examples/example_subscriptionconfirmation.json
django_bouncy-0.2.8.dist-info/LICENSE
django_bouncy-0.2.8.dist-info/METADATA
django_bouncy-0.2.8.dist-info/WHEEL
django_bouncy-0.2.8.dist-info/top_level.txt
django_bouncy-0.2.8.dist-info/RECORD
