Metadata-Version: 2.1
Name: django-bouncy
Version: 0.2.8
Summary: A way to handle bounce and abuse reports delivered by Amazon's Simple Notification Service regarding emails sent by Simple Email Service
Home-page: https://github.com/organizerconnect/django-bouncy
Author: Nick Catalano
Author-email: UNKNOWN
License: UNKNOWN
Keywords: aws ses sns seacucumber boto
Platform: UNKNOWN
Classifier: Development Status :: 4 - Beta
Classifier: Intended Audience :: Developers
Classifier: Topic :: Internet :: WWW/HTTP
Requires-Dist: Django (>=1.11)
Requires-Dist: python-dateutil (>=2.1)
Requires-Dist: pyopenssl (>=0.13.1)
Requires-Dist: pem (>=16.0.0)
